setup.py
brynq_sdk_azure/__init__.py
brynq_sdk_azure/azure_connection.py
brynq_sdk_azure/blob_storage.py
brynq_sdk_azure/entra.py
brynq_sdk_azure.egg-info/PKG-INFO
brynq_sdk_azure.egg-info/SOURCES.txt
brynq_sdk_azure.egg-info/dependency_links.txt
brynq_sdk_azure.egg-info/not-zip-safe
brynq_sdk_azure.egg-info/requires.txt
brynq_sdk_azure.egg-info/top_level.txt