Metadata-Version: 1.0
Name: brynq-sdk-azure
Version: 2.0.3
Summary: Azure wrapper from BrynQ
Home-page: UNKNOWN
Author: BrynQ
Author-email: support@brynq.com
License: BrynQ License
Platform: UNKNOWN
